openlineage/dbt/__init__.py
openlineage_dbt-1.42.1.dist-info/WHEEL
openlineage_dbt-1.42.1.dist-info/entry_points.txt
openlineage_dbt-1.42.1.dist-info/METADATA
openlineage_dbt-1.42.1.dist-info/RECORD
