Metadata-Version: 2.3
Name: openlineage-dbt
Version: 1.42.1
Summary: OpenLineage integration with dbt
Keywords: openlineage
Author: OpenLineage
Requires-Dist: tqdm>=4.62.0
Requires-Dist: openlineage-integration-common==1.42.1
Requires-Dist: dbt-core>=1.0.0
Requires-Dist: pytest>=7.0.0 ; extra == 'dev'
Requires-Dist: pytest-cov ; extra == 'dev'
Requires-Dist: pytest-xdist>=2.5.0 ; extra == 'dev'
Requires-Dist: mock ; extra == 'dev'
Requires-Dist: ruff ; extra == 'dev'
Requires-Dist: mypy>=0.9.6 ; extra == 'dev'
Requires-Dist: python-dateutil ; extra == 'dev'
Requires-Dist: requests>=2.25.0 ; extra == 'dev'
Requires-Dist: docker>=6.0.0 ; extra == 'dev'
Requires-Dist: mypy ; extra == 'dev'
Requires-Python: >=3.9
Provides-Extra: dev
